{
  "pools": [
    {
      "rolls": 1,
      "entries": [
        {
          "type": "minecraft:item",
          "name": "passionprojectmod:gem",
          "conditions": [
            {
              "condition": "minecraft:random_chance",
              "chance": 0.4
            },
            {
              "condition": "minecraft:location_check",
              "predicate": {
                "location": {
                  "biome": "minecraft:dark_forest"
                }
              }
            }
          ]
        }
      ]
    }
  ]
}